{"SelectedTraceFilePath":"C:\\Users\\oesezer\\Desktop\\From-Adi\\CM_PerformanceTest_Logging.pcapng","SelectedCatalogFolderPath":"C:\\TIDE\\Projects\\Trace Replay\\config\\busCatalogs\\fern","UILanguage":0,"NumOfTxMessagesToBeSent":10000,"TxDelayTolerance":20,"TxMessagePeriod":1.0,"ApplyTxMessageLimit":true,"ByPassHardwareTx":false,"ByPassProgressUpdate":false,"IsCmModEmuRunningLocal":false,"PlpTxMessageCycle":5.0,"IsPlpMsgTimeChanging":true,"PlpTimeSyncInterval":1.0,"ShowSplashScreen":false,"SaveSettings":true,"SaveDockLayout":true,"DeleteOldImages":true}